.travis.yml
AUTHORS
LICENSE
MANIFEST.in
README.rst
setup.cfg
setup.py
Mopidy_WebLibrary.egg-info/PKG-INFO
Mopidy_WebLibrary.egg-info/SOURCES.txt
Mopidy_WebLibrary.egg-info/dependency_links.txt
Mopidy_WebLibrary.egg-info/entry_points.txt
Mopidy_WebLibrary.egg-info/not-zip-safe
Mopidy_WebLibrary.egg-info/requires.txt
Mopidy_WebLibrary.egg-info/top_level.txt
mopidy_weblibrary/__init__.py
mopidy_weblibrary/ext.conf
mopidy_weblibrary/web.py
mopidy_weblibrary/webclient.py
mopidy_weblibrary/static/index.html
mopidy_weblibrary/static/mb.appcache
mopidy_weblibrary/static/cors/postmessage.html
mopidy_weblibrary/static/cors/result.html
mopidy_weblibrary/static/css/blueimp-gallery.min.css
mopidy_weblibrary/static/css/demo.css
mopidy_weblibrary/static/css/jquery-ui.css
mopidy_weblibrary/static/css/jquery.fileupload-noscript.css
mopidy_weblibrary/static/css/jquery.fileupload-ui-noscript.css
mopidy_weblibrary/static/css/jquery.fileupload-ui.css
mopidy_weblibrary/static/css/jquery.fileupload.css
mopidy_weblibrary/static/css/style.css
mopidy_weblibrary/static/img/default_cover.png
mopidy_weblibrary/static/img/empty.png
mopidy_weblibrary/static/img/loader.gif
mopidy_weblibrary/static/img/loading.gif
mopidy_weblibrary/static/img/progressbar.gif
mopidy_weblibrary/static/vendors/jquery.ui.widget.js
mopidy_weblibrary/static/vendors/font_awesome/css/font-awesome.css
mopidy_weblibrary/static/vendors/font_awesome/css/font-awesome.min.css
mopidy_weblibrary/static/vendors/font_awesome/fonts/FontAwesome.otf
mopidy_weblibrary/static/vendors/font_awesome/fonts/fontawesome-webfont.eot
mopidy_weblibrary/static/vendors/font_awesome/fonts/fontawesome-webfont.svg
mopidy_weblibrary/static/vendors/font_awesome/fonts/fontawesome-webfont.ttf
mopidy_weblibrary/static/vendors/font_awesome/fonts/fontawesome-webfont.woff
mopidy_weblibrary/static/vendors/font_awesome/fonts/fontawesome-webfont.woff2
mopidy_weblibrary/static/vendors/font_awesome/less/animated.less
mopidy_weblibrary/static/vendors/font_awesome/less/bordered-pulled.less
mopidy_weblibrary/static/vendors/font_awesome/less/core.less
mopidy_weblibrary/static/vendors/font_awesome/less/fixed-width.less
mopidy_weblibrary/static/vendors/font_awesome/less/font-awesome.less
mopidy_weblibrary/static/vendors/font_awesome/less/icons.less
