Metadata-Version: 1.1
Name: Mopidy-WebLibrary
Version: 1.0.0
Summary: Mopidy extension for editing the music library in a web interface
Home-page: https://github.com/fbarresi/Mopidy-WebLibrary
Author: Federico Barresi
Author-email: fede.barresi@gmail.com
License: Apache License, Version 2.0
Platform: UNKNOWN
Classifier: Environment :: No Input/Output (Daemon)
Classifier: Intended Audience :: End Users/Desktop
Classifier: License :: OSI Approved :: Apache Software License
Classifier: Operating System :: OS Independent
Classifier: Programming Language :: Python :: 2
Classifier: Topic :: Multimedia :: Sound/Audio :: Players
